[{"id": 1, "name": "Siemens", "instType": "UK_Industry"}, {"id": 2, "name": "East Anglia", "instType": "UK_University"}, {"id": 3, "name": "London South Bank", "instType": "UK_University", "numProjects": 2, "Funding": 607817}, {"id": 4, "name": "West of Scotland", "instType": "UK_University", "numProjects": 2, "Funding": 1259327.5274999999}, {"id": 5, "name": "Glasgow", "instType": "UK_University"}, {"id": 6, "name": "Home Office", "instType": "UK_Industry"}, {"id": 7, "name": "Nokia", "instType": "UK_Industry"}, {"id": 8, "name": "Loughborough", "instType": "UK_University", "numProjects": 1, "Funding": 0.0}, {"id": 9, "name": "Southampton", "instType": "UK_University"}, {"id": 10, "name": "Rinicom", "instType": "UK_Industry"}, {"id": 11, "name": "Queen's Belfast", "instType": "UK_University", "numProjects": 8, "Funding": 910461.0}, {"id": 12, "name": "Intel", "instType": "UK_Industry"}, {"id": 13, "name": "Heriot-Watt", "instType": "UK_University", "numProjects": 3, "Funding": 6489564}, {"id": 14, "name": "Alcatel Lucent", "instType": "UK_Industry"}, {"id": 15, "name": "Northampton", "instType": "UK_University", "numProjects": 2, "Funding": 99771.0}, {"id": 16, "name": "Real Wireless", "instType": "UK_Industry"}, {"id": 17, "name": "Liverpool John Moores", "instType": "UK_University", "numProjects": 1, "Funding": 100786}, {"id": 18, "name": "Blu Wireless", "instType": "UK_Industry"}, {"id": 19, "name": "Edinburgh", "instType": "UK_University", "numProjects": 1, "Funding": 0.0}, {"id": 20, "name": "Thales", "instType": "UK_Industry"}, {"id": 22, "name": "Imperial College London", "instType": "UK_University", "numProjects": 4, "Funding": 1519974.62}, {"id": 23, "name": "Queen Mary", "instType": "UK_University", "numProjects": 4, "Funding": 0.0}, {"id": 24, "name": "Quortus", "instType": "UK_Industry"}, {"id": 25, "name": "Kent", "instType": "UK_University"}, {"id": 26, "name": "UCL", "instType": "UK_University", "numProjects": 16, "Funding": 10056328.945}, {"id": 27, "name": "ADVA Optical", "instType": "UK_Industry"}, {"id": 28, "name": "Toshiba", "instType": "UK_Industry"}, {"id": 29, "name": "Sheffield", "instType": "UK_University", "numProjects": 1, "Funding": 0.0}, {"id": 30, "name": "Dell", "instType": "UK_Industry"}, {"id": 31, "name": "TRL", "instType": "UK_Industry"}, {"id": 32, "name": "Samsung", "instType": "UK_Industry"}, {"id": 33, "name": "Birmingham", "instType": "UK_University", "numProjects": 2, "Funding": 743439.0}, {"id": 34, "name": "Future Intelligence Ltd", "instType": "UK_Industry"}, {"id": 35, "name": "Airbus", "instType": "UK_Industry"}, {"id": 36, "name": "King's College London", "instType": "UK_University", "numProjects": 19, "Funding": 9334105.0692}, {"id": 37, "name": "Geant", "instType": "UK_Industry"}, {"id": 38, "name": "IBM", "instType": "UK_Industry"}, {"id": 39, "name": "EE", "instType": "UK_Industry"}, {"id": 40, "name": "Brighton", "instType": "UK_University", "numProjects": 1, "Funding": 295158.4875}, {"id": 41, "name": "Cisco", "instType": "UK_Industry"}, {"id": 42, "name": "Oxford", "instType": "UK_University", "numProjects": 18, "Funding": 9174020.9225}, {"id": 44, "name": "Kingston", "instType": "UK_University"}, {"id": 45, "name": "Fujitsu", "instType": "UK_Industry"}, {"id": 46, "name": "Bangor University", "instType": "UK_Industry"}, {"id": 47, "name": "SONY", "instType": "UK_Industry"}, {"id": 48, "name": "QinetiQ", "instType": "UK_Industry"}, {"id": 49, "name": "Bristol", "instType": "UK_University", "numProjects": 19, "Funding": 5840949.91}, {"id": 50, "name": "Cardiff", "instType": "UK_University", "numProjects": 2, "Funding": 1999999}, {"id": 51, "name": "NEC", "instType": "UK_Industry"}, {"id": 52, "name": "BAE", "instType": "UK_Industry"}, {"id": 54, "name": "Ubitech", "instType": "UK_Industry"}, {"id": 55, "name": "Liverpool", "instType": "UK_University", "numProjects": 2, "Funding": 210325.0}, {"id": 56, "name": "InterDigital", "instType": "UK_Industry"}, {"id": 57, "name": "Zeetta", "instType": "UK_Industry"}, {"id": 58, "name": "Essex", "instType": "UK_University", "numProjects": 5, "Funding": 1776210.525}, {"id": 60, "name": "Sony", "instType": "UK_Industry"}, {"id": 61, "name": "Surrey", "instType": "UK_University", "numProjects": 2, "Funding": 0.0}, {"id": 62, "name": "York", "instType": "UK_University", "numProjects": 10, "Funding": 585892.4264}, {"id": 63, "name": "Warwick", "instType": "UK_University"}, {"id": 64, "name": "Avanti", "instType": "UK_Industry"}, {"id": 65, "name": "Manchester", "instType": "UK_University", "numProjects": 4, "Funding": 2024684.0}, {"id": 66, "name": "Newcastle", "instType": "UK_University"}, {"id": 67, "name": "Cambridge", "instType": "UK_University", "numProjects": 2, "Funding": 0.0}, {"id": 68, "name": "Lancaster", "instType": "UK_University", "numProjects": 2, "Funding": 0.0}]